emmet/api/API.py
emmet/api/__init__.py
emmet/api/default_responses.yaml
emmet/api/models.py
emmet/api/py.typed
emmet/api/utils.py
emmet/api/core/__init__.py
emmet/api/core/api.py
emmet/api/core/documentation.py
emmet/api/core/global_header.py
emmet/api/core/settings.py
emmet/api/core/assets/mp_logo.svg
emmet/api/core/assets/mp_logo_small.png
emmet/api/query_operator/__init__.py
emmet/api/query_operator/core.py
emmet/api/query_operator/dynamic.py
emmet/api/query_operator/pagination.py
emmet/api/query_operator/sorting.py
emmet/api/query_operator/sparse_fields.py
emmet/api/query_operator/submission.py
emmet/api/resource/__init__.py
emmet/api/resource/aggregation.py
emmet/api/resource/core.py
emmet/api/resource/post_resource.py
emmet/api/resource/read_resource.py
emmet/api/resource/submission.py
emmet/api/resource/utils.py
emmet/api/routes/__init__.py
emmet/api/routes/_consumer/__init__.py
emmet/api/routes/_consumer/query_operator.py
emmet/api/routes/_consumer/resources.py
emmet/api/routes/_general_store/__init__.py
emmet/api/routes/_general_store/query_operator.py
emmet/api/routes/_general_store/resources.py
emmet/api/routes/_messages/__init__.py
emmet/api/routes/_messages/query_operator.py
emmet/api/routes/_messages/resources.py
emmet/api/routes/defects/tasks/__init__.py
emmet/api/routes/defects/tasks/resources.py
emmet/api/routes/dois/__init__.py
emmet/api/routes/dois/resources.py
emmet/api/routes/legacy/__init__.py
emmet/api/routes/legacy/jcesr/__init__.py
emmet/api/routes/legacy/jcesr/query_operators.py
emmet/api/routes/legacy/jcesr/resources.py
emmet/api/routes/materials/__init__.py
emmet/api/routes/materials/absorption/__init__.py
emmet/api/routes/materials/absorption/resources.py
emmet/api/routes/materials/alloys/__init__.py
emmet/api/routes/materials/alloys/query_operators.py
emmet/api/routes/materials/alloys/resources.py
emmet/api/routes/materials/bonds/__init__.py
emmet/api/routes/materials/bonds/query_operators.py
emmet_api-0.86.3.dist-info/METADATA
emmet_api-0.86.3.dist-info/WHEEL
emmet_api-0.86.3.dist-info/top_level.txt
emmet_api-0.86.3.dist-info/RECORD
